gwPythonSecTt1/__init__.py
gwPythonSecTt1/module1.py
gwPythonSecTt1-0.1.dist-info/METADATA
gwPythonSecTt1-0.1.dist-info/WHEEL
gwPythonSecTt1-0.1.dist-info/top_level.txt
gwPythonSecTt1-0.1.dist-info/RECORD
